[{"date&time": "2019-03-14 14:53 (Thursday", "1st_quote_post": 1, "1st_quote_stack": 2, "1st_quote_buyout": 610000, "2nd_quote_post": 1, "2nd_quote_stack": 2, "2nd_quote_buyout": 740000, "3rd_quote_post": 1, "3rd_quote_stack": 54, "3rd_quote_buyout": 740702}, {"date&time": "2019-03-14 15:09 (Thursday", "1st_quote_post": 3, "1st_quote_stack": 1, "1st_quote_buyout": 739900, "2nd_quote_post": 1, "2nd_quote_stack": 2, "2nd_quote_buyout": 740000, "3rd_quote_post": 1, "3rd_quote_stack": 54, "3rd_quote_buyout": 740702}, {"date&time": "2019-03-14 15:26 (Thursday", "1st_quote_post": 1, "1st_quote_stack": 2, "1st_quote_buyout": 732000, "2nd_quote_post": 3, "2nd_quote_stack": 1, "2nd_quote_buyout": 739900, "3rd_quote_post": 1, "3rd_quote_stack": 2, "3rd_quote_buyout": 740000}, {"date&time": "2019-03-14 15:39 (Thursday", "1st_quote_post": 1, "1st_quote_stack": 2, "1st_quote_buyout": 732000, "2nd_quote_post": 3, "2nd_quote_stack": 1, "2nd_quote_buyout": 739900, "3rd_quote_post": 1, "3rd_quote_stack": 2, "3rd_quote_buyout": 740000}, {"date&time": "2019-03-14 15:49 (Thursday", "1st_quote_post": 1, "1st_quote_stack": 3, "1st_quote_buyout": 500000, "2nd_quote_post": 1, "2nd_quote_stack": 2, "2nd_quote_buyout": 732000, "3rd_quote_post": 3, "3rd_quote_stack": 1, "3rd_quote_buyout": 739900}, {"date&time": "2019-03-14 15:58 (Thursday", "1st_quote_post": 1, "1st_quote_stack": 2, "1st_quote_buyout": 732000, "2nd_quote_post": 3, "2nd_quote_stack": 1, "2nd_quote_buyout": 739900, "3rd_quote_post": 1, "3rd_quote_stack": 2, "3rd_quote_buyout": 740000}, {"date&time": "2019-03-14 16:27 (Thursday", "1st_quote_post": 1, "1st_quote_stack": 2, "1st_quote_buyout": 732000, "2nd_quote_post": 3, "2nd_quote_stack": 1, "2nd_quote_buyout": 739900, "3rd_quote_post": 1, "3rd_quote_stack": 2, "3rd_quote_buyout": 740000}, {"date&time": "2019-03-14 16:40 (Thursday", "1st_quote_post": 1, "1st_quote_stack": 2, "1st_quote_buyout": 732000, "2nd_quote_post": 3, "2nd_quote_stack": 1, "2nd_quote_buyout": 739900, "3rd_quote_post": 1, "3rd_quote_stack": 2, "3rd_quote_buyout": 740000}, {"date&time": "2019-03-14 16:53 (Thursday", "1st_quote_post": 1, "1st_quote_stack": 9, "1st_quote_buyout": 700016, "2nd_quote_post": 1, "2nd_quote_stack": 2, "2nd_quote_buyout": 732000, "3rd_quote_post": 2, "3rd_quote_stack": 1, "3rd_quote_buyout": 739900}, {"date&time": "2019-03-14 17:07 (Thursday", "1st_quote_post": 1, "1st_quote_stack": 2, "1st_quote_buyout": 693000, "2nd_quote_post": 1, "2nd_quote_stack": 9, "2nd_quote_buyout": 700016, "3rd_quote_post": 1, "3rd_quote_stack": 2, "3rd_quote_buyout": 732000}, {"date&time": "2019-03-14 17:20 (Thursday", "1st_quote_post": 1, "1st_quote_stack": 1, "1st_quote_buyout": 570100, "2nd_quote_post": 1, "2nd_quote_stack": 2, "2nd_quote_buyout": 600000, "3rd_quote_post": 1, "3rd_quote_stack": 3, "3rd_quote_buyout": 600000}, {"date&time": "2019-03-14 17:34 (Thursday", "1st_quote_post": 1, "1st_quote_stack": 3, "1st_quote_buyout": 564000, "2nd_quote_post": 1, "2nd_quote_stack": 1, "2nd_quote_buyout": 570150, "3rd_quote_post": 1, "3rd_quote_stack": 2, "3rd_quote_buyout": 600000}, {"date&time": "2019-03-14 17:49 (Thursday", "1st_quote_post": 1, "1st_quote_stack": 3, "1st_quote_buyout": 564000, "2nd_quote_post": 1, "2nd_quote_stack": 2, "2nd_quote_buyout": 600000, "3rd_quote_post": 1, "3rd_quote_stack": 3, "3rd_quote_buyout": 600000}, {"date&time": "2019-03-14 18:02 (Thursday", "1st_quote_post": 1, "1st_quote_stack": 1, "1st_quote_buyout": 750000, "2nd_quote_post": 18, "2nd_quote_stack": 1, "2nd_quote_buyout": 754000, "3rd_quote_post": 1, "3rd_quote_stack": 94, "3rd_quote_buyout": 800100}, {"date&time": "2019-03-14 18:17 (Thursday", "1st_quote_post": 1, "1st_quote_stack": 1, "1st_quote_buyout": 750000, "2nd_quote_post": 10, "2nd_quote_stack": 3, "2nd_quote_buyout": 753900, "3rd_quote_post": 18, "3rd_quote_stack": 1, "3rd_quote_buyout": 754000}, {"date&time": "2019-03-14 18:49 (Thursday", "1st_quote_post": 18, "1st_quote_stack": 1, "1st_quote_buyout": 754000, "2nd_quote_post": 1, "2nd_quote_stack": 94, "2nd_quote_buyout": 790000, "3rd_quote_post": 7, "3rd_quote_stack": 100, "3rd_quote_buyout": 790000}, {"date&time": "2019-03-14 19:04 (Thursday", "1st_quote_post": 1, "1st_quote_stack": 2, "1st_quote_buyout": 750150, "2nd_quote_post": 18, "2nd_quote_stack": 1, "2nd_quote_buyout": 754000, "3rd_quote_post": 5, "3rd_quote_stack": 100, "3rd_quote_buyout": 790000}, {"date&time": "2019-03-14 19:19 (Thursday", "1st_quote_post": 1, "1st_quote_stack": 8, "1st_quote_buyout": 651207, "2nd_quote_post": 20, "2nd_quote_stack": 1, "2nd_quote_buyout": 750000, "3rd_quote_post": 1, "3rd_quote_stack": 2, "3rd_quote_buyout": 750150}, {"date&time": "2019-03-14 19:35 (Thursday", "1st_quote_post": 1, "1st_quote_stack": 8, "1st_quote_buyout": 651207, "2nd_quote_post": 1, "2nd_quote_stack": 29, "2nd_quote_buyout": 730000, "3rd_quote_post": 20, "3rd_quote_stack": 1, "3rd_quote_buyout": 750000}, {"date&time": "2019-03-14 19:53 (Thursday", "1st_quote_post": 1, "1st_quote_stack": 8, "1st_quote_buyout": 651207, "2nd_quote_post": 1, "2nd_quote_stack": 17, "2nd_quote_buyout": 700100, "3rd_quote_post": 1, "3rd_quote_stack": 29, "3rd_quote_buyout": 730000}, {"date&time": "2019-03-14 20:09 (Thursday", "1st_quote_post": 9, "1st_quote_stack": 1, "1st_quote_buyout": 750000, "2nd_quote_post": 1, "2nd_quote_stack": 2, "2nd_quote_buyout": 750100, "3rd_quote_post": 18, "3rd_quote_stack": 1, "3rd_quote_buyout": 754000}, {"date&time": "2019-03-14 20:26 (Thursday", "1st_quote_post": 9, "1st_quote_stack": 1, "1st_quote_buyout": 750000, "2nd_quote_post": 1, "2nd_quote_stack": 2, "2nd_quote_buyout": 750100, "3rd_quote_post": 18, "3rd_quote_stack": 1, "3rd_quote_buyout": 754000}, {"date&time": "2019-03-14 20:42 (Thursday", "1st_quote_post": 2, "1st_quote_stack": 1, "1st_quote_buyout": 730100, "2nd_quote_post": 9, "2nd_quote_stack": 1, "2nd_quote_buyout": 750000, "3rd_quote_post": 1, "3rd_quote_stack": 2, "3rd_quote_buyout": 750150}, {"date&time": "2019-03-14 21:18 (Thursday", "1st_quote_post": 1, "1st_quote_stack": 4, "1st_quote_buyout": 700000, "2nd_quote_post": 1, "2nd_quote_stack": 1, "2nd_quote_buyout": 700000, "3rd_quote_post": 2, "3rd_quote_stack": 1, "3rd_quote_buyout": 730100}, {"date&time": "2019-03-14 21:33 (Thursday", "1st_quote_post": 1, "1st_quote_stack": 4, "1st_quote_buyout": 700000, "2nd_quote_post": 1, "2nd_quote_stack": 1, "2nd_quote_buyout": 700000, "3rd_quote_post": 2, "3rd_quote_stack": 1, "3rd_quote_buyout": 730100}, {"date&time": "2019-03-14 21:48 (Thursday", "1st_quote_post": 1, "1st_quote_stack": 4, "1st_quote_buyout": 700000, "2nd_quote_post": 1, "2nd_quote_stack": 1, "2nd_quote_buyout": 700000, "3rd_quote_post": 1, "3rd_quote_stack": 2, "3rd_quote_buyout": 700075}, {"date&time": "2019-03-14 22:18 (Thursday", "1st_quote_post": 1, "1st_quote_stack": 20, "1st_quote_buyout": 820000, "2nd_quote_post": 29, "2nd_quote_stack": 20, "2nd_quote_buyout": 820000, "3rd_quote_post": 1, "3rd_quote_stack": 70, "3rd_quote_buyout": 821000}, {"date&time": "2019-03-14 22:34 (Thursday", "1st_quote_post": 1, "1st_quote_stack": 20, "1st_quote_buyout": 820000, "2nd_quote_post": 29, "2nd_quote_stack": 20, "2nd_quote_buyout": 820000, "3rd_quote_post": 1, "3rd_quote_stack": 70, "3rd_quote_buyout": 821000}, {"date&time": "2019-03-14 22:49 (Thursday", "1st_quote_post": 7, "1st_quote_stack": 50, "1st_quote_buyout": 800000, "2nd_quote_post": 1, "2nd_quote_stack": 20, "2nd_quote_buyout": 820000, "3rd_quote_post": 25, "3rd_quote_stack": 20, "3rd_quote_buyout": 820000}, {"date&time": "2019-03-14 23:05 (Thursday", "1st_quote_post": 1, "1st_quote_stack": 5, "1st_quote_buyout": 762000, "2nd_quote_post": 1, "2nd_quote_stack": 3, "2nd_quote_buyout": 770150, "3rd_quote_post": 1, "3rd_quote_stack": 1, "3rd_quote_buyout": 770100}, {"date&time": "2019-03-14 23:20 (Thursday", "1st_quote_post": 1, "1st_quote_stack": 3, "1st_quote_buyout": 770100, "2nd_quote_post": 1, "2nd_quote_stack": 1, "2nd_quote_buyout": 770150, "3rd_quote_post": 7, "3rd_quote_stack": 50, "3rd_quote_buyout": 800000}, {"date&time": "2019-03-14 23:36 (Thursday", "1st_quote_post": 1, "1st_quote_stack": 53, "1st_quote_buyout": 790099, "2nd_quote_post": 1, "2nd_quote_stack": 8, "2nd_quote_buyout": 790100, "3rd_quote_post": 7, "3rd_quote_stack": 50, "3rd_quote_buyout": 800000}, {"date&time": "2019-03-15 08:13 (Friday", "1st_quote_post": 1, "1st_quote_stack": 59, "1st_quote_buyout": 700005, "2nd_quote_post": 5, "2nd_quote_stack": 10, "2nd_quote_buyout": 750100, "3rd_quote_post": 1, "3rd_quote_stack": 93, "3rd_quote_buyout": 789900}, {"date&time": "2019-03-15 08:27 (Friday", "1st_quote_post": 5, "1st_quote_stack": 50, "1st_quote_buyout": 680000, "2nd_quote_post": 1, "2nd_quote_stack": 59, "2nd_quote_buyout": 700005, "3rd_quote_post": 5, "3rd_quote_stack": 10, "3rd_quote_buyout": 750150}, {"date&time": "2019-03-15 08:40 (Friday", "1st_quote_post": 5, "1st_quote_stack": 50, "1st_quote_buyout": 680000, "2nd_quote_post": 1, "2nd_quote_stack": 59, "2nd_quote_buyout": 700005, "3rd_quote_post": 5, "3rd_quote_stack": 10, "3rd_quote_buyout": 750150}, {"date&time": "2019-03-15 08:53 (Friday", "1st_quote_post": 5, "1st_quote_stack": 50, "1st_quote_buyout": 680000, "2nd_quote_post": 1, "2nd_quote_stack": 59, "2nd_quote_buyout": 700005, "3rd_quote_post": 5, "3rd_quote_stack": 10, "3rd_quote_buyout": 750150}, {"date&time": "2019-03-15 09:05 (Friday", "1st_quote_post": 5, "1st_quote_stack": 50, "1st_quote_buyout": 680000, "2nd_quote_post": 1, "2nd_quote_stack": 59, "2nd_quote_buyout": 700005, "3rd_quote_post": 5, "3rd_quote_stack": 10, "3rd_quote_buyout": 750150}, {"date&time": "2019-03-15 09:37 (Friday", "1st_quote_post": 4, "1st_quote_stack": 50, "1st_quote_buyout": 680000, "2nd_quote_post": 1, "2nd_quote_stack": 59, "2nd_quote_buyout": 700005, "3rd_quote_post": 5, "3rd_quote_stack": 10, "3rd_quote_buyout": 750150}, {"date&time": "2019-03-15 09:53 (Friday", "1st_quote_post": 4, "1st_quote_stack": 50, "1st_quote_buyout": 680000, "2nd_quote_post": 1, "2nd_quote_stack": 59, "2nd_quote_buyout": 700005, "3rd_quote_post": 5, "3rd_quote_stack": 10, "3rd_quote_buyout": 750150}, {"date&time": "2019-03-15 10:10 (Friday", "1st_quote_post": 1, "1st_quote_stack": 2, "1st_quote_buyout": 670100, "2nd_quote_post": 4, "2nd_quote_stack": 50, "2nd_quote_buyout": 680000, "3rd_quote_post": 1, "3rd_quote_stack": 59, "3rd_quote_buyout": 700005}, {"date&time": "2019-03-15 10:32 (Friday", "1st_quote_post": 1, "1st_quote_stack": 200, "1st_quote_buyout": 670149, "2nd_quote_post": 1, "2nd_quote_stack": 61, "2nd_quote_buyout": 670149, "3rd_quote_post": 1, "3rd_quote_stack": 2, "3rd_quote_buyout": 670100}, {"date&time": "2019-03-15 10:48 (Friday", "1st_quote_post": 1, "1st_quote_stack": 59, "1st_quote_buyout": 700005, "2nd_quote_post": 1, "2nd_quote_stack": 104, "2nd_quote_buyout": 750000, "3rd_quote_post": 5, "3rd_quote_stack": 10, "3rd_quote_buyout": 750150}, {"date&time": "2019-03-15 11:04 (Friday", "1st_quote_post": 1, "1st_quote_stack": 59, "1st_quote_buyout": 700005, "2nd_quote_post": 1, "2nd_quote_stack": 104, "2nd_quote_buyout": 750000, "3rd_quote_post": 5, "3rd_quote_stack": 10, "3rd_quote_buyout": 750150}, {"date&time": "2019-03-15 11:20 (Friday", "1st_quote_post": 1, "1st_quote_stack": 3, "1st_quote_buyout": 693000, "2nd_quote_post": 1, "2nd_quote_stack": 59, "2nd_quote_buyout": 700005, "3rd_quote_post": 1, "3rd_quote_stack": 104, "3rd_quote_buyout": 750000}, {"date&time": "2019-03-15 11:37 (Friday", "1st_quote_post": 1, "1st_quote_stack": 3, "1st_quote_buyout": 693000, "2nd_quote_post": 1, "2nd_quote_stack": 59, "2nd_quote_buyout": 700005, "3rd_quote_post": 1, "3rd_quote_stack": 104, "3rd_quote_buyout": 750000}, {"date&time": "2019-03-15 12:02 (Friday", "1st_quote_post": 1, "1st_quote_stack": 4, "1st_quote_buyout": 660100, "2nd_quote_post": 1, "2nd_quote_stack": 1, "2nd_quote_buyout": 660100, "3rd_quote_post": 1, "3rd_quote_stack": 3, "3rd_quote_buyout": 693000}, {"date&time": "2019-03-15 12:20 (Friday", "1st_quote_post": 1, "1st_quote_stack": 4, "1st_quote_buyout": 660100, "2nd_quote_post": 1, "2nd_quote_stack": 1, "2nd_quote_buyout": 660100, "3rd_quote_post": 1, "3rd_quote_stack": 3, "3rd_quote_buyout": 693000}, {"date&time": "2019-03-15 12:39 (Friday", "1st_quote_post": 1, "1st_quote_stack": 25, "1st_quote_buyout": 700100, "2nd_quote_post": 1, "2nd_quote_stack": 51, "2nd_quote_buyout": 740100, "3rd_quote_post": 2, "3rd_quote_stack": 200, "3rd_quote_buyout": 750000}, {"date&time": "2019-03-15 12:56 (Friday", "1st_quote_post": 9, "1st_quote_stack": 40, "1st_quote_buyout": 688808, "2nd_quote_post": 1, "2nd_quote_stack": 25, "2nd_quote_buyout": 700100, "3rd_quote_post": 1, "3rd_quote_stack": 551, "3rd_quote_buyout": 740100}, {"date&time": "2019-03-15 13:12 (Friday", "1st_quote_post": 9, "1st_quote_stack": 40, "1st_quote_buyout": 688808, "2nd_quote_post": 1, "2nd_quote_stack": 25, "2nd_quote_buyout": 700100, "3rd_quote_post": 1, "3rd_quote_stack": 551, "3rd_quote_buyout": 740100}, {"date&time": "2019-03-15 13:30 (Friday", "1st_quote_post": 1, "1st_quote_stack": 33, "1st_quote_buyout": 687400, "2nd_quote_post": 8, "2nd_quote_stack": 40, "2nd_quote_buyout": 688808, "3rd_quote_post": 1, "3rd_quote_stack": 25, "3rd_quote_buyout": 700100}, {"date&time": "2019-03-15 15:30 (Friday", "1st_quote_post": 1, "1st_quote_stack": 1, "1st_quote_buyout": 672000, "2nd_quote_post": 2, "2nd_quote_stack": 94, "2nd_quote_buyout": 679000, "3rd_quote_post": 1, "3rd_quote_stack": 2, "3rd_quote_buyout": 680075}, {"date&time": "2019-03-15 15:48 (Friday", "1st_quote_post": 1, "1st_quote_stack": 1, "1st_quote_buyout": 655000, "2nd_quote_post": 1, "2nd_quote_stack": 9, "2nd_quote_buyout": 671999, "3rd_quote_post": 1, "3rd_quote_stack": 1, "3rd_quote_buyout": 672000}, {"date&time": "2019-03-15 16:07 (Friday", "1st_quote_post": 1, "1st_quote_stack": 1, "1st_quote_buyout": 655000, "2nd_quote_post": 1, "2nd_quote_stack": 9, "2nd_quote_buyout": 671999, "3rd_quote_post": 1, "3rd_quote_stack": 1, "3rd_quote_buyout": 672000}, {"date&time": "2019-03-15 16:22 (Friday", "1st_quote_post": 1, "1st_quote_stack": 12, "1st_quote_buyout": 648000, "2nd_quote_post": 1, "2nd_quote_stack": 7, "2nd_quote_buyout": 654999, "3rd_quote_post": 1, "3rd_quote_stack": 1, "3rd_quote_buyout": 655000}, {"date&time": "2019-03-15 16:38 (Friday", "1st_quote_post": 1, "1st_quote_stack": 12, "1st_quote_buyout": 648000, "2nd_quote_post": 1, "2nd_quote_stack": 7, "2nd_quote_buyout": 654999, "3rd_quote_post": 1, "3rd_quote_stack": 1, "3rd_quote_buyout": 655000}, {"date&time": "2019-03-15 16:55 (Friday", "1st_quote_post": 1, "1st_quote_stack": 199, "1st_quote_buyout": 647000, "2nd_quote_post": 1, "2nd_quote_stack": 105, "2nd_quote_buyout": 647000, "3rd_quote_post": 1, "3rd_quote_stack": 12, "3rd_quote_buyout": 648000}, {"date&time": "2019-03-15 17:12 (Friday", "1st_quote_post": 1, "1st_quote_stack": 149, "1st_quote_buyout": 640037, "2nd_quote_post": 1, "2nd_quote_stack": 20, "2nd_quote_buyout": 640099, "3rd_quote_post": 1, "3rd_quote_stack": 199, "3rd_quote_buyout": 647000}, {"date&time": "2019-03-15 17:28 (Friday", "1st_quote_post": 1, "1st_quote_stack": 16, "1st_quote_buyout": 618055, "2nd_quote_post": 1, "2nd_quote_stack": 149, "2nd_quote_buyout": 640003, "3rd_quote_post": 1, "3rd_quote_stack": 20, "3rd_quote_buyout": 640099}, {"date&time": "2019-03-15 17:45 (Friday", "1st_quote_post": 1, "1st_quote_stack": 22, "1st_quote_buyout": 580150, "2nd_quote_post": 1, "2nd_quote_stack": 1, "2nd_quote_buyout": 600100, "3rd_quote_post": 1, "3rd_quote_stack": 16, "3rd_quote_buyout": 618055}, {"date&time": "2019-03-15 18:01 (Friday", "1st_quote_post": 1, "1st_quote_stack": 128, "1st_quote_buyout": 579000, "2nd_quote_post": 1, "2nd_quote_stack": 22, "2nd_quote_buyout": 580150, "3rd_quote_post": 1, "3rd_quote_stack": 1, "3rd_quote_buyout": 600100}, {"date&time": "2019-03-15 18:19 (Friday", "1st_quote_post": 1, "1st_quote_stack": 128, "1st_quote_buyout": 579000, "2nd_quote_post": 1, "2nd_quote_stack": 22, "2nd_quote_buyout": 580150, "3rd_quote_post": 1, "3rd_quote_stack": 1, "3rd_quote_buyout": 600100}, {"date&time": "2019-03-15 18:35 (Friday", "1st_quote_post": 1, "1st_quote_stack": 128, "1st_quote_buyout": 579000, "2nd_quote_post": 1, "2nd_quote_stack": 22, "2nd_quote_buyout": 580150, "3rd_quote_post": 1, "3rd_quote_stack": 1, "3rd_quote_buyout": 600100}, {"date&time": "2019-03-15 18:52 (Friday", "1st_quote_post": 1, "1st_quote_stack": 128, "1st_quote_buyout": 579000, "2nd_quote_post": 1, "2nd_quote_stack": 1, "2nd_quote_buyout": 600100, "3rd_quote_post": 1, "3rd_quote_stack": 200, "3rd_quote_buyout": 643000}]