[{"date&time": "2019-03-11 18:56 (Monday", "1st_quote_post": 11, "1st_quote_stack": 100, "1st_quote_buyout": 95443, "2nd_quote_post": 1, "2nd_quote_stack": 100, "2nd_quote_buyout": 95443, "3rd_quote_post": 3, "3rd_quote_stack": 200, "3rd_quote_buyout": 95444}, {"date&time": "2019-03-11 19:02 (Monday", "1st_quote_post": 5, "1st_quote_stack": 200, "1st_quote_buyout": 90504, "2nd_quote_post": 1, "2nd_quote_stack": 100, "2nd_quote_buyout": 95443, "3rd_quote_post": 11, "3rd_quote_stack": 100, "3rd_quote_buyout": 95443}, {"date&time": "2019-03-11 19:14 (Monday", "1st_quote_post": 4, "1st_quote_stack": 50, "1st_quote_buyout": 95000, "2nd_quote_post": 5, "2nd_quote_stack": 200, "2nd_quote_buyout": 90554, "3rd_quote_post": 1, "3rd_quote_stack": 100, "3rd_quote_buyout": 95443}, {"date&time": "2019-03-11 19:18 (Monday", "1st_quote_post": 4, "1st_quote_stack": 50, "1st_quote_buyout": 95000, "2nd_quote_post": 5, "2nd_quote_stack": 200, "2nd_quote_buyout": 90554, "3rd_quote_post": 1, "3rd_quote_stack": 100, "3rd_quote_buyout": 95443}, {"date&time": "2019-03-11 19:34 (Monday", "1st_quote_post": 4, "1st_quote_stack": 50, "1st_quote_buyout": 95000, "2nd_quote_post": 1, "2nd_quote_stack": 138, "2nd_quote_buyout": 95100, "3rd_quote_post": 3, "3rd_quote_stack": 200, "3rd_quote_buyout": 95100}, {"date&time": "2019-03-11 19:41 (Monday", "1st_quote_post": 4, "1st_quote_stack": 50, "1st_quote_buyout": 95000, "2nd_quote_post": 1, "2nd_quote_stack": 138, "2nd_quote_buyout": 95100, "3rd_quote_post": 3, "3rd_quote_stack": 200, "3rd_quote_buyout": 95100}, {"date&time": "2019-03-11 19:56 (Monday", "1st_quote_post": 1, "1st_quote_stack": 30, "1st_quote_buyout": 93362, "2nd_quote_post": 4, "2nd_quote_stack": 50, "2nd_quote_buyout": 95000, "3rd_quote_post": 1, "3rd_quote_stack": 138, "3rd_quote_buyout": 95100}, {"date&time": "2019-03-11 20:01 (Monday", "1st_quote_post": 1, "1st_quote_stack": 30, "1st_quote_buyout": 93362, "2nd_quote_post": 4, "2nd_quote_stack": 50, "2nd_quote_buyout": 95000, "3rd_quote_post": 3, "3rd_quote_stack": 100, "3rd_quote_buyout": 95099}, {"date&time": "2019-03-11 20:09 (Monday", "1st_quote_post": 1, "1st_quote_stack": 2, "1st_quote_buyout": 84099, "2nd_quote_post": 1, "2nd_quote_stack": 30, "2nd_quote_buyout": 93362, "3rd_quote_post": 4, "3rd_quote_stack": 50, "3rd_quote_buyout": 95000}, {"date&time": "2019-03-11 20:16 (Monday", "1st_quote_post": 1, "1st_quote_stack": 2, "1st_quote_buyout": 84099, "2nd_quote_post": 3, "2nd_quote_stack": 50, "2nd_quote_buyout": 95000, "3rd_quote_post": 3, "3rd_quote_stack": 100, "3rd_quote_buyout": 95099}, {"date&time": "2019-03-11 20:23 (Monday", "1st_quote_post": 1, "1st_quote_stack": 2, "1st_quote_buyout": 84099, "2nd_quote_post": 3, "2nd_quote_stack": 50, "2nd_quote_buyout": 95000, "3rd_quote_post": 3, "3rd_quote_stack": 100, "3rd_quote_buyout": 95099}, {"date&time": "2019-03-11 20:31 (Monday", "1st_quote_post": 1, "1st_quote_stack": 2, "1st_quote_buyout": 84099, "2nd_quote_post": 14, "2nd_quote_stack": 200, "2nd_quote_buyout": 90306, "3rd_quote_post": 3, "3rd_quote_stack": 50, "3rd_quote_buyout": 95000}, {"date&time": "2019-03-11 20:40 (Monday", "1st_quote_post": 1, "1st_quote_stack": 2, "1st_quote_buyout": 84099, "2nd_quote_post": 3, "2nd_quote_stack": 100, "2nd_quote_buyout": 93866, "3rd_quote_post": 14, "3rd_quote_stack": 200, "3rd_quote_buyout": 90306}, {"date&time": "2019-03-11 20:43 (Monday", "1st_quote_post": 1, "1st_quote_stack": 158, "1st_quote_buyout": 82318, "2nd_quote_post": 1, "2nd_quote_stack": 200, "2nd_quote_buyout": 82762, "3rd_quote_post": 1, "3rd_quote_stack": 2, "3rd_quote_buyout": 84099}, {"date&time": "2019-03-11 20:51 (Monday", "1st_quote_post": 2, "1st_quote_stack": 100, "1st_quote_buyout": 82317, "2nd_quote_post": 1, "2nd_quote_stack": 158, "2nd_quote_buyout": 82318, "3rd_quote_post": 1, "3rd_quote_stack": 200, "3rd_quote_buyout": 82762}, {"date&time": "2019-03-11 20:56 (Monday", "1st_quote_post": 2, "1st_quote_stack": 100, "1st_quote_buyout": 82317, "2nd_quote_post": 1, "2nd_quote_stack": 158, "2nd_quote_buyout": 82318, "3rd_quote_post": 1, "3rd_quote_stack": 200, "3rd_quote_buyout": 82762}, {"date&time": "2019-03-11 21:01 (Monday", "1st_quote_post": 2, "1st_quote_stack": 100, "1st_quote_buyout": 82317, "2nd_quote_post": 1, "2nd_quote_stack": 158, "2nd_quote_buyout": 82318, "3rd_quote_post": 1, "3rd_quote_stack": 200, "3rd_quote_buyout": 82762}, {"date&time": "2019-03-11 21:08 (Monday", "1st_quote_post": 2, "1st_quote_stack": 100, "1st_quote_buyout": 82317, "2nd_quote_post": 1, "2nd_quote_stack": 158, "2nd_quote_buyout": 82318, "3rd_quote_post": 1, "3rd_quote_stack": 200, "3rd_quote_buyout": 82762}, {"date&time": "2019-03-11 21:15 (Monday", "1st_quote_post": 2, "1st_quote_stack": 100, "1st_quote_buyout": 82317, "2nd_quote_post": 1, "2nd_quote_stack": 158, "2nd_quote_buyout": 82318, "3rd_quote_post": 1, "3rd_quote_stack": 200, "3rd_quote_buyout": 82762}, {"date&time": "2019-03-11 21:21 (Monday", "1st_quote_post": 2, "1st_quote_stack": 100, "1st_quote_buyout": 82317, "2nd_quote_post": 1, "2nd_quote_stack": 158, "2nd_quote_buyout": 82318, "3rd_quote_post": 1, "3rd_quote_stack": 200, "3rd_quote_buyout": 82762}, {"date&time": "2019-03-11 21:27 (Monday", "1st_quote_post": 2, "1st_quote_stack": 100, "1st_quote_buyout": 82317, "2nd_quote_post": 1, "2nd_quote_stack": 158, "2nd_quote_buyout": 82318, "3rd_quote_post": 1, "3rd_quote_stack": 200, "3rd_quote_buyout": 82762}, {"date&time": "2019-03-11 21:34 (Monday", "1st_quote_post": 2, "1st_quote_stack": 100, "1st_quote_buyout": 82317, "2nd_quote_post": 1, "2nd_quote_stack": 158, "2nd_quote_buyout": 82318, "3rd_quote_post": 1, "3rd_quote_stack": 200, "3rd_quote_buyout": 82762}, {"date&time": "2019-03-11 21:41 (Monday", "1st_quote_post": 2, "1st_quote_stack": 100, "1st_quote_buyout": 82317, "2nd_quote_post": 1, "2nd_quote_stack": 158, "2nd_quote_buyout": 82318, "3rd_quote_post": 1, "3rd_quote_stack": 200, "3rd_quote_buyout": 82762}, {"date&time": "2019-03-11 21:48 (Monday", "1st_quote_post": 2, "1st_quote_stack": 100, "1st_quote_buyout": 82317, "2nd_quote_post": 1, "2nd_quote_stack": 158, "2nd_quote_buyout": 82318, "3rd_quote_post": 1, "3rd_quote_stack": 200, "3rd_quote_buyout": 82762}, {"date&time": "2019-03-11 21:55 (Monday", "1st_quote_post": 2, "1st_quote_stack": 100, "1st_quote_buyout": 82317, "2nd_quote_post": 1, "2nd_quote_stack": 158, "2nd_quote_buyout": 82318, "3rd_quote_post": 1, "3rd_quote_stack": 200, "3rd_quote_buyout": 82762}, {"date&time": "2019-03-11 22:02 (Monday", "1st_quote_post": 2, "1st_quote_stack": 100, "1st_quote_buyout": 82317, "2nd_quote_post": 1, "2nd_quote_stack": 158, "2nd_quote_buyout": 82318, "3rd_quote_post": 1, "3rd_quote_stack": 200, "3rd_quote_buyout": 82762}, {"date&time": "2019-03-11 22:08 (Monday", "1st_quote_post": 2, "1st_quote_stack": 100, "1st_quote_buyout": 82317, "2nd_quote_post": 1, "2nd_quote_stack": 158, "2nd_quote_buyout": 82318, "3rd_quote_post": 1, "3rd_quote_stack": 200, "3rd_quote_buyout": 82762}, {"date&time": "2019-03-11 22:15 (Monday", "1st_quote_post": 4, "1st_quote_stack": 50, "1st_quote_buyout": 82000, "2nd_quote_post": 2, "2nd_quote_stack": 100, "2nd_quote_buyout": 82317, "3rd_quote_post": 1, "3rd_quote_stack": 158, "3rd_quote_buyout": 82318}, {"date&time": "2019-03-11 22:23 (Monday", "1st_quote_post": 1, "1st_quote_stack": 50, "1st_quote_buyout": 81400, "2nd_quote_post": 4, "2nd_quote_stack": 50, "2nd_quote_buyout": 82000, "3rd_quote_post": 2, "3rd_quote_stack": 100, "3rd_quote_buyout": 82317}, {"date&time": "2019-03-11 22:30 (Monday", "1st_quote_post": 1, "1st_quote_stack": 50, "1st_quote_buyout": 81400, "2nd_quote_post": 4, "2nd_quote_stack": 50, "2nd_quote_buyout": 82000, "3rd_quote_post": 2, "3rd_quote_stack": 100, "3rd_quote_buyout": 82317}, {"date&time": "2019-03-11 22:36 (Monday", "1st_quote_post": 1, "1st_quote_stack": 50, "1st_quote_buyout": 81400, "2nd_quote_post": 4, "2nd_quote_stack": 50, "2nd_quote_buyout": 82000, "3rd_quote_post": 2, "3rd_quote_stack": 100, "3rd_quote_buyout": 82317}, {"date&time": "2019-03-11 22:41 (Monday", "1st_quote_post": 1, "1st_quote_stack": 50, "1st_quote_buyout": 81400, "2nd_quote_post": 4, "2nd_quote_stack": 50, "2nd_quote_buyout": 82000, "3rd_quote_post": 2, "3rd_quote_stack": 100, "3rd_quote_buyout": 82317}, {"date&time": "2019-03-11 22:48 (Monday", "1st_quote_post": 1, "1st_quote_stack": 50, "1st_quote_buyout": 81400, "2nd_quote_post": 4, "2nd_quote_stack": 50, "2nd_quote_buyout": 82000, "3rd_quote_post": 2, "3rd_quote_stack": 100, "3rd_quote_buyout": 82317}, {"date&time": "2019-03-11 22:54 (Monday", "1st_quote_post": 1, "1st_quote_stack": 50, "1st_quote_buyout": 81400, "2nd_quote_post": 4, "2nd_quote_stack": 50, "2nd_quote_buyout": 82000, "3rd_quote_post": 2, "3rd_quote_stack": 100, "3rd_quote_buyout": 82317}, {"date&time": "2019-03-11 23:00 (Monday", "1st_quote_post": 1, "1st_quote_stack": 50, "1st_quote_buyout": 81400, "2nd_quote_post": 4, "2nd_quote_stack": 50, "2nd_quote_buyout": 82000, "3rd_quote_post": 2, "3rd_quote_stack": 100, "3rd_quote_buyout": 82317}, {"date&time": "2019-03-11 23:06 (Monday", "1st_quote_post": 1, "1st_quote_stack": 50, "1st_quote_buyout": 81400, "2nd_quote_post": 4, "2nd_quote_stack": 50, "2nd_quote_buyout": 82000, "3rd_quote_post": 2, "3rd_quote_stack": 100, "3rd_quote_buyout": 82317}, {"date&time": "2019-03-11 23:13 (Monday", "1st_quote_post": 1, "1st_quote_stack": 50, "1st_quote_buyout": 81400, "2nd_quote_post": 4, "2nd_quote_stack": 50, "2nd_quote_buyout": 82000, "3rd_quote_post": 2, "3rd_quote_stack": 100, "3rd_quote_buyout": 82317}, {"date&time": "2019-03-11 23:22 (Monday", "1st_quote_post": 3, "1st_quote_stack": 50, "1st_quote_buyout": 82000, "2nd_quote_post": 2, "2nd_quote_stack": 100, "2nd_quote_buyout": 82317, "3rd_quote_post": 1, "3rd_quote_stack": 158, "3rd_quote_buyout": 82318}, {"date&time": "2019-03-11 23:28 (Monday", "1st_quote_post": 3, "1st_quote_stack": 50, "1st_quote_buyout": 82000, "2nd_quote_post": 2, "2nd_quote_stack": 100, "2nd_quote_buyout": 82317, "3rd_quote_post": 1, "3rd_quote_stack": 158, "3rd_quote_buyout": 82318}, {"date&time": "2019-03-11 23:33 (Monday", "1st_quote_post": 3, "1st_quote_stack": 50, "1st_quote_buyout": 82000, "2nd_quote_post": 2, "2nd_quote_stack": 100, "2nd_quote_buyout": 82317, "3rd_quote_post": 1, "3rd_quote_stack": 158, "3rd_quote_buyout": 82318}, {"date&time": "2019-03-11 23:41 (Monday", "1st_quote_post": 3, "1st_quote_stack": 50, "1st_quote_buyout": 82000, "2nd_quote_post": 2, "2nd_quote_stack": 100, "2nd_quote_buyout": 82317, "3rd_quote_post": 1, "3rd_quote_stack": 158, "3rd_quote_buyout": 82318}, {"date&time": "2019-03-11 23:48 (Monday", "1st_quote_post": 3, "1st_quote_stack": 50, "1st_quote_buyout": 82000, "2nd_quote_post": 2, "2nd_quote_stack": 100, "2nd_quote_buyout": 82317, "3rd_quote_post": 1, "3rd_quote_stack": 158, "3rd_quote_buyout": 82318}, {"date&time": "2019-03-11 23:53 (Monday", "1st_quote_post": 3, "1st_quote_stack": 50, "1st_quote_buyout": 82000, "2nd_quote_post": 2, "2nd_quote_stack": 100, "2nd_quote_buyout": 82317, "3rd_quote_post": 1, "3rd_quote_stack": 158, "3rd_quote_buyout": 82318}, {"date&time": "2019-03-12 00:00 (Tuesday", "1st_quote_post": 3, "1st_quote_stack": 50, "1st_quote_buyout": 82000, "2nd_quote_post": 2, "2nd_quote_stack": 100, "2nd_quote_buyout": 82317, "3rd_quote_post": 1, "3rd_quote_stack": 158, "3rd_quote_buyout": 82318}, {"date&time": "2019-03-12 00:06 (Tuesday", "1st_quote_post": 3, "1st_quote_stack": 50, "1st_quote_buyout": 82000, "2nd_quote_post": 2, "2nd_quote_stack": 100, "2nd_quote_buyout": 82317, "3rd_quote_post": 1, "3rd_quote_stack": 158, "3rd_quote_buyout": 82318}, {"date&time": "2019-03-12 00:13 (Tuesday", "1st_quote_post": 3, "1st_quote_stack": 50, "1st_quote_buyout": 82000, "2nd_quote_post": 2, "2nd_quote_stack": 100, "2nd_quote_buyout": 82317, "3rd_quote_post": 1, "3rd_quote_stack": 158, "3rd_quote_buyout": 82318}, {"date&time": "2019-03-12 00:20 (Tuesday", "1st_quote_post": 3, "1st_quote_stack": 50, "1st_quote_buyout": 82000, "2nd_quote_post": 2, "2nd_quote_stack": 100, "2nd_quote_buyout": 82317, "3rd_quote_post": 1, "3rd_quote_stack": 158, "3rd_quote_buyout": 82318}, {"date&time": "2019-03-12 00:25 (Tuesday", "1st_quote_post": 3, "1st_quote_stack": 50, "1st_quote_buyout": 82000, "2nd_quote_post": 2, "2nd_quote_stack": 100, "2nd_quote_buyout": 82317, "3rd_quote_post": 1, "3rd_quote_stack": 158, "3rd_quote_buyout": 82318}, {"date&time": "2019-03-12 00:32 (Tuesday", "1st_quote_post": 3, "1st_quote_stack": 50, "1st_quote_buyout": 82000, "2nd_quote_post": 2, "2nd_quote_stack": 100, "2nd_quote_buyout": 82317, "3rd_quote_post": 1, "3rd_quote_stack": 158, "3rd_quote_buyout": 82318}, {"date&time": "2019-03-12 00:40 (Tuesday", "1st_quote_post": 3, "1st_quote_stack": 50, "1st_quote_buyout": 82000, "2nd_quote_post": 2, "2nd_quote_stack": 100, "2nd_quote_buyout": 82317, "3rd_quote_post": 1, "3rd_quote_stack": 158, "3rd_quote_buyout": 82318}, {"date&time": "2019-03-12 00:46 (Tuesday", "1st_quote_post": 3, "1st_quote_stack": 50, "1st_quote_buyout": 82000, "2nd_quote_post": 2, "2nd_quote_stack": 100, "2nd_quote_buyout": 82317, "3rd_quote_post": 1, "3rd_quote_stack": 158, "3rd_quote_buyout": 82318}, {"date&time": "2019-03-12 00:52 (Tuesday", "1st_quote_post": 1, "1st_quote_stack": 50, "1st_quote_buyout": 81000, "2nd_quote_post": 3, "2nd_quote_stack": 50, "2nd_quote_buyout": 82000, "3rd_quote_post": 2, "3rd_quote_stack": 100, "3rd_quote_buyout": 82317}, {"date&time": "2019-03-12 01:00 (Tuesday", "1st_quote_post": 1, "1st_quote_stack": 50, "1st_quote_buyout": 81000, "2nd_quote_post": 3, "2nd_quote_stack": 50, "2nd_quote_buyout": 82000, "3rd_quote_post": 2, "3rd_quote_stack": 100, "3rd_quote_buyout": 82317}, {"date&time": "2019-03-12 01:07 (Tuesday", "1st_quote_post": 1, "1st_quote_stack": 50, "1st_quote_buyout": 81000, "2nd_quote_post": 3, "2nd_quote_stack": 50, "2nd_quote_buyout": 82000, "3rd_quote_post": 2, "3rd_quote_stack": 100, "3rd_quote_buyout": 82317}, {"date&time": "2019-03-12 01:22 (Tuesday", "1st_quote_post": 1, "1st_quote_stack": 50, "1st_quote_buyout": 81000, "2nd_quote_post": 3, "2nd_quote_stack": 50, "2nd_quote_buyout": 82000, "3rd_quote_post": 2, "3rd_quote_stack": 100, "3rd_quote_buyout": 82317}, {"date&time": "2019-03-12 01:27 (Tuesday", "1st_quote_post": 1, "1st_quote_stack": 50, "1st_quote_buyout": 81000, "2nd_quote_post": 3, "2nd_quote_stack": 50, "2nd_quote_buyout": 82000, "3rd_quote_post": 2, "3rd_quote_stack": 100, "3rd_quote_buyout": 82317}, {"date&time": "2019-03-12 01:34 (Tuesday", "1st_quote_post": 1, "1st_quote_stack": 50, "1st_quote_buyout": 81000, "2nd_quote_post": 3, "2nd_quote_stack": 50, "2nd_quote_buyout": 82000, "3rd_quote_post": 2, "3rd_quote_stack": 100, "3rd_quote_buyout": 82317}, {"date&time": "2019-03-12 01:41 (Tuesday", "1st_quote_post": 1, "1st_quote_stack": 50, "1st_quote_buyout": 81000, "2nd_quote_post": 3, "2nd_quote_stack": 50, "2nd_quote_buyout": 82000, "3rd_quote_post": 2, "3rd_quote_stack": 100, "3rd_quote_buyout": 82317}, {"date&time": "2019-03-12 01:48 (Tuesday", "1st_quote_post": 1, "1st_quote_stack": 50, "1st_quote_buyout": 81000, "2nd_quote_post": 3, "2nd_quote_stack": 50, "2nd_quote_buyout": 82000, "3rd_quote_post": 2, "3rd_quote_stack": 100, "3rd_quote_buyout": 82317}, {"date&time": "2019-03-12 01:53 (Tuesday", "1st_quote_post": 1, "1st_quote_stack": 50, "1st_quote_buyout": 81000, "2nd_quote_post": 3, "2nd_quote_stack": 50, "2nd_quote_buyout": 82000, "3rd_quote_post": 2, "3rd_quote_stack": 100, "3rd_quote_buyout": 82317}, {"date&time": "2019-03-12 02:00 (Tuesday", "1st_quote_post": 1, "1st_quote_stack": 50, "1st_quote_buyout": 81000, "2nd_quote_post": 3, "2nd_quote_stack": 50, "2nd_quote_buyout": 82000, "3rd_quote_post": 2, "3rd_quote_stack": 100, "3rd_quote_buyout": 82317}, {"date&time": "2019-03-12 02:05 (Tuesday", "1st_quote_post": 1, "1st_quote_stack": 19, "1st_quote_buyout": 74057, "2nd_quote_post": 1, "2nd_quote_stack": 50, "2nd_quote_buyout": 81000, "3rd_quote_post": 3, "3rd_quote_stack": 50, "3rd_quote_buyout": 82000}, {"date&time": "2019-03-12 02:13 (Tuesday", "1st_quote_post": 1, "1st_quote_stack": 19, "1st_quote_buyout": 74057, "2nd_quote_post": 1, "2nd_quote_stack": 50, "2nd_quote_buyout": 81000, "3rd_quote_post": 3, "3rd_quote_stack": 50, "3rd_quote_buyout": 82000}, {"date&time": "2019-03-12 02:21 (Tuesday", "1st_quote_post": 1, "1st_quote_stack": 19, "1st_quote_buyout": 74057, "2nd_quote_post": 1, "2nd_quote_stack": 50, "2nd_quote_buyout": 81000, "3rd_quote_post": 3, "3rd_quote_stack": 50, "3rd_quote_buyout": 82000}, {"date&time": "2019-03-12 02:28 (Tuesday", "1st_quote_post": 1, "1st_quote_stack": 19, "1st_quote_buyout": 74057, "2nd_quote_post": 1, "2nd_quote_stack": 50, "2nd_quote_buyout": 81000, "3rd_quote_post": 3, "3rd_quote_stack": 50, "3rd_quote_buyout": 82000}, {"date&time": "2019-03-12 02:33 (Tuesday", "1st_quote_post": 1, "1st_quote_stack": 19, "1st_quote_buyout": 74057, "2nd_quote_post": 1, "2nd_quote_stack": 50, "2nd_quote_buyout": 81000, "3rd_quote_post": 3, "3rd_quote_stack": 50, "3rd_quote_buyout": 82000}, {"date&time": "2019-03-12 02:39 (Tuesday", "1st_quote_post": 1, "1st_quote_stack": 19, "1st_quote_buyout": 74057, "2nd_quote_post": 1, "2nd_quote_stack": 50, "2nd_quote_buyout": 81000, "3rd_quote_post": 3, "3rd_quote_stack": 50, "3rd_quote_buyout": 82000}, {"date&time": "2019-03-12 02:45 (Tuesday", "1st_quote_post": 1, "1st_quote_stack": 19, "1st_quote_buyout": 74057, "2nd_quote_post": 1, "2nd_quote_stack": 50, "2nd_quote_buyout": 81000, "3rd_quote_post": 3, "3rd_quote_stack": 50, "3rd_quote_buyout": 82000}, {"date&time": "2019-03-12 02:52 (Tuesday", "1st_quote_post": 1, "1st_quote_stack": 19, "1st_quote_buyout": 74057, "2nd_quote_post": 1, "2nd_quote_stack": 50, "2nd_quote_buyout": 81000, "3rd_quote_post": 3, "3rd_quote_stack": 50, "3rd_quote_buyout": 82000}, {"date&time": "2019-03-12 02:59 (Tuesday", "1st_quote_post": 1, "1st_quote_stack": 19, "1st_quote_buyout": 74057, "2nd_quote_post": 1, "2nd_quote_stack": 50, "2nd_quote_buyout": 81000, "3rd_quote_post": 3, "3rd_quote_stack": 50, "3rd_quote_buyout": 82000}, {"date&time": "2019-03-12 03:07 (Tuesday", "1st_quote_post": 1, "1st_quote_stack": 19, "1st_quote_buyout": 74057, "2nd_quote_post": 1, "2nd_quote_stack": 50, "2nd_quote_buyout": 81000, "3rd_quote_post": 3, "3rd_quote_stack": 50, "3rd_quote_buyout": 82000}, {"date&time": "2019-03-12 03:13 (Tuesday", "1st_quote_post": 1, "1st_quote_stack": 19, "1st_quote_buyout": 74057, "2nd_quote_post": 1, "2nd_quote_stack": 50, "2nd_quote_buyout": 81000, "3rd_quote_post": 3, "3rd_quote_stack": 50, "3rd_quote_buyout": 82000}, {"date&time": "2019-03-12 03:20 (Tuesday", "1st_quote_post": 1, "1st_quote_stack": 19, "1st_quote_buyout": 74057, "2nd_quote_post": 1, "2nd_quote_stack": 50, "2nd_quote_buyout": 81000, "3rd_quote_post": 3, "3rd_quote_stack": 50, "3rd_quote_buyout": 82000}, {"date&time": "2019-03-12 07:42 (Tuesday", "1st_quote_post": 1, "1st_quote_stack": 20, "1st_quote_buyout": 79999, "2nd_quote_post": 1, "2nd_quote_stack": 50, "2nd_quote_buyout": 81000, "3rd_quote_post": 3, "3rd_quote_stack": 50, "3rd_quote_buyout": 82000}, {"date&time": "2019-03-12 09:38 (Tuesday", "1st_quote_post": 1, "1st_quote_stack": 20, "1st_quote_buyout": 79999, "2nd_quote_post": 13, "2nd_quote_stack": 200, "2nd_quote_buyout": 80967, "3rd_quote_post": 1, "3rd_quote_stack": 50, "3rd_quote_buyout": 81000}, {"date&time": "2019-03-12 09:51 (Tuesday", "1st_quote_post": 1, "1st_quote_stack": 20, "1st_quote_buyout": 79999, "2nd_quote_post": 9, "2nd_quote_stack": 100, "2nd_quote_buyout": 80906, "3rd_quote_post": 13, "3rd_quote_stack": 200, "3rd_quote_buyout": 80007}, {"date&time": "2019-03-12 10:00 (Tuesday", "1st_quote_post": 1, "1st_quote_stack": 26, "1st_quote_buyout": 72646, "2nd_quote_post": 1, "2nd_quote_stack": 20, "2nd_quote_buyout": 79999, "3rd_quote_post": 9, "3rd_quote_stack": 100, "3rd_quote_buyout": 80906}, {"date&time": "2019-03-12 10:19 (Tuesday", "1st_quote_post": 1, "1st_quote_stack": 26, "1st_quote_buyout": 72646, "2nd_quote_post": 1, "2nd_quote_stack": 20, "2nd_quote_buyout": 79999, "3rd_quote_post": 9, "3rd_quote_stack": 100, "3rd_quote_buyout": 80906}, {"date&time": "2019-03-12 11:03 (Tuesday", "1st_quote_post": 1, "1st_quote_stack": 1, "1st_quote_buyout": 71900, "2nd_quote_post": 1, "2nd_quote_stack": 26, "2nd_quote_buyout": 72646, "3rd_quote_post": 1, "3rd_quote_stack": 20, "3rd_quote_buyout": 79999}, {"date&time": "2019-03-12 11:08 (Tuesday", "1st_quote_post": 1, "1st_quote_stack": 1, "1st_quote_buyout": 71900, "2nd_quote_post": 1, "2nd_quote_stack": 26, "2nd_quote_buyout": 72646, "3rd_quote_post": 1, "3rd_quote_stack": 20, "3rd_quote_buyout": 79999}, {"date&time": "2019-03-12 11:17 (Tuesday", "1st_quote_post": 1, "1st_quote_stack": 1, "1st_quote_buyout": 71900, "2nd_quote_post": 1, "2nd_quote_stack": 26, "2nd_quote_buyout": 72646, "3rd_quote_post": 1, "3rd_quote_stack": 20, "3rd_quote_buyout": 79999}, {"date&time": "2019-03-12 11:41 (Tuesday", "1st_quote_post": 1, "1st_quote_stack": 6, "1st_quote_buyout": 70000, "2nd_quote_post": 1, "2nd_quote_stack": 1, "2nd_quote_buyout": 71900, "3rd_quote_post": 1, "3rd_quote_stack": 26, "3rd_quote_buyout": 72646}, {"date&time": "2019-03-12 12:06 (Tuesday", "1st_quote_post": 1, "1st_quote_stack": 6, "1st_quote_buyout": 70000, "2nd_quote_post": 1, "2nd_quote_stack": 1, "2nd_quote_buyout": 71900, "3rd_quote_post": 1, "3rd_quote_stack": 20, "3rd_quote_buyout": 79999}, {"date&time": "2019-03-12 12:22 (Tuesday", "1st_quote_post": 1, "1st_quote_stack": 6, "1st_quote_buyout": 70000, "2nd_quote_post": 1, "2nd_quote_stack": 1, "2nd_quote_buyout": 71900, "3rd_quote_post": 1, "3rd_quote_stack": 100, "3rd_quote_buyout": 80806}, {"date&time": "2019-03-12 12:39 (Tuesday", "1st_quote_post": 1, "1st_quote_stack": 6, "1st_quote_buyout": 70000, "2nd_quote_post": 1, "2nd_quote_stack": 1, "2nd_quote_buyout": 71900, "3rd_quote_post": 1, "3rd_quote_stack": 100, "3rd_quote_buyout": 80806}, {"date&time": "2019-03-12 12:56 (Tuesday", "1st_quote_post": 1, "1st_quote_stack": 6, "1st_quote_buyout": 70000, "2nd_quote_post": 1, "2nd_quote_stack": 1, "2nd_quote_buyout": 71900, "3rd_quote_post": 1, "3rd_quote_stack": 100, "3rd_quote_buyout": 80806}, {"date&time": "2019-03-12 13:17 (Tuesday", "1st_quote_post": 1, "1st_quote_stack": 6, "1st_quote_buyout": 70000, "2nd_quote_post": 1, "2nd_quote_stack": 1, "2nd_quote_buyout": 71900, "3rd_quote_post": 1, "3rd_quote_stack": 100, "3rd_quote_buyout": 80806}, {"date&time": "2019-03-12 13:32 (Tuesday", "1st_quote_post": 5, "1st_quote_stack": 200, "1st_quote_buyout": 80963, "2nd_quote_post": 8, "2nd_quote_stack": 100, "2nd_quote_buyout": 80906, "3rd_quote_post": 13, "3rd_quote_stack": 200, "3rd_quote_buyout": 80007}, {"date&time": "2019-03-12 13:40 (Tuesday", "1st_quote_post": 5, "1st_quote_stack": 200, "1st_quote_buyout": 80963, "2nd_quote_post": 8, "2nd_quote_stack": 100, "2nd_quote_buyout": 80906, "3rd_quote_post": 13, "3rd_quote_stack": 200, "3rd_quote_buyout": 80007}, {"date&time": "2019-03-12 13:45 (Tuesday", "1st_quote_post": 5, "1st_quote_stack": 100, "1st_quote_buyout": 80002, "2nd_quote_post": 5, "2nd_quote_stack": 200, "2nd_quote_buyout": 80963, "3rd_quote_post": 8, "3rd_quote_stack": 100, "3rd_quote_buyout": 80906}, {"date&time": "2019-03-12 14:04 (Tuesday", "1st_quote_post": 5, "1st_quote_stack": 100, "1st_quote_buyout": 80002, "2nd_quote_post": 5, "2nd_quote_stack": 200, "2nd_quote_buyout": 80963, "3rd_quote_post": 8, "3rd_quote_stack": 100, "3rd_quote_buyout": 80906}, {"date&time": "2019-03-12 14:26 (Tuesday", "1st_quote_post": 4, "1st_quote_stack": 10, "1st_quote_buyout": 74000, "2nd_quote_post": 5, "2nd_quote_stack": 100, "2nd_quote_buyout": 80962, "3rd_quote_post": 5, "3rd_quote_stack": 200, "3rd_quote_buyout": 80963}, {"date&time": "2019-03-12 14:47 (Tuesday", "1st_quote_post": 4, "1st_quote_stack": 10, "1st_quote_buyout": 74000, "2nd_quote_post": 4, "2nd_quote_stack": 100, "2nd_quote_buyout": 80962, "3rd_quote_post": 5, "3rd_quote_stack": 200, "3rd_quote_buyout": 80963}, {"date&time": "2019-03-12 15:07 (Tuesday", "1st_quote_post": 4, "1st_quote_stack": 10, "1st_quote_buyout": 74000, "2nd_quote_post": 3, "2nd_quote_stack": 200, "2nd_quote_buyout": 80960, "3rd_quote_post": 3, "3rd_quote_stack": 100, "3rd_quote_buyout": 80960}, {"date&time": "2019-03-12 15:26 (Tuesday", "1st_quote_post": 4, "1st_quote_stack": 10, "1st_quote_buyout": 74000, "2nd_quote_post": 6, "2nd_quote_stack": 100, "2nd_quote_buyout": 80959, "3rd_quote_post": 3, "3rd_quote_stack": 200, "3rd_quote_buyout": 80960}, {"date&time": "2019-03-12 15:44 (Tuesday", "1st_quote_post": 4, "1st_quote_stack": 10, "1st_quote_buyout": 74000, "2nd_quote_post": 6, "2nd_quote_stack": 100, "2nd_quote_buyout": 80959, "3rd_quote_post": 3, "3rd_quote_stack": 200, "3rd_quote_buyout": 80960}, {"date&time": "2019-03-12 16:18 (Tuesday", "1st_quote_post": 4, "1st_quote_stack": 10, "1st_quote_buyout": 74000, "2nd_quote_post": 13, "2nd_quote_stack": 200, "2nd_quote_buyout": 80867, "3rd_quote_post": 6, "3rd_quote_stack": 100, "3rd_quote_buyout": 80959}, {"date&time": "2019-03-12 16:41 (Tuesday", "1st_quote_post": 4, "1st_quote_stack": 10, "1st_quote_buyout": 74000, "2nd_quote_post": 8, "2nd_quote_stack": 100, "2nd_quote_buyout": 80806, "3rd_quote_post": 13, "3rd_quote_stack": 200, "3rd_quote_buyout": 80006}, {"date&time": "2019-03-12 16:58 (Tuesday", "1st_quote_post": 4, "1st_quote_stack": 10, "1st_quote_buyout": 74000, "2nd_quote_post": 8, "2nd_quote_stack": 100, "2nd_quote_buyout": 80806, "3rd_quote_post": 13, "3rd_quote_stack": 200, "3rd_quote_buyout": 80006}, {"date&time": "2019-03-12 17:19 (Tuesday", "1st_quote_post": 4, "1st_quote_stack": 10, "1st_quote_buyout": 74000, "2nd_quote_post": 8, "2nd_quote_stack": 100, "2nd_quote_buyout": 80806, "3rd_quote_post": 13, "3rd_quote_stack": 200, "3rd_quote_buyout": 80006}, {"date&time": "2019-03-12 17:31 (Tuesday", "1st_quote_post": 4, "1st_quote_stack": 10, "1st_quote_buyout": 74000, "2nd_quote_post": 8, "2nd_quote_stack": 100, "2nd_quote_buyout": 80806, "3rd_quote_post": 13, "3rd_quote_stack": 200, "3rd_quote_buyout": 80006}, {"date&time": "2019-03-12 17:49 (Tuesday", "1st_quote_post": 4, "1st_quote_stack": 10, "1st_quote_buyout": 74000, "2nd_quote_post": 8, "2nd_quote_stack": 100, "2nd_quote_buyout": 80806, "3rd_quote_post": 13, "3rd_quote_stack": 200, "3rd_quote_buyout": 80006}, {"date&time": "2019-03-12 18:05 (Tuesday", "1st_quote_post": 4, "1st_quote_stack": 10, "1st_quote_buyout": 74000, "2nd_quote_post": 7, "2nd_quote_stack": 100, "2nd_quote_buyout": 80806, "3rd_quote_post": 13, "3rd_quote_stack": 200, "3rd_quote_buyout": 80006}, {"date&time": "2019-03-12 18:18 (Tuesday", "1st_quote_post": 4, "1st_quote_stack": 10, "1st_quote_buyout": 74000, "2nd_quote_post": 7, "2nd_quote_stack": 100, "2nd_quote_buyout": 80806, "3rd_quote_post": 13, "3rd_quote_stack": 200, "3rd_quote_buyout": 80006}, {"date&time": "2019-03-12 18:31 (Tuesday", "1st_quote_post": 1, "1st_quote_stack": 14, "1st_quote_buyout": 64285, "2nd_quote_post": 1, "2nd_quote_stack": 121, "2nd_quote_buyout": 72500, "3rd_quote_post": 4, "3rd_quote_stack": 10, "3rd_quote_buyout": 74000}, {"date&time": "2019-03-12 18:48 (Tuesday", "1st_quote_post": 1, "1st_quote_stack": 14, "1st_quote_buyout": 64285, "2nd_quote_post": 7, "2nd_quote_stack": 100, "2nd_quote_buyout": 72499, "3rd_quote_post": 1, "3rd_quote_stack": 121, "3rd_quote_buyout": 72500}, {"date&time": "2019-03-12 19:06 (Tuesday", "1st_quote_post": 1, "1st_quote_stack": 14, "1st_quote_buyout": 64285, "2nd_quote_post": 7, "2nd_quote_stack": 100, "2nd_quote_buyout": 72499, "3rd_quote_post": 1, "3rd_quote_stack": 121, "3rd_quote_buyout": 72500}, {"date&time": "2019-03-12 19:26 (Tuesday", "1st_quote_post": 7, "1st_quote_stack": 100, "1st_quote_buyout": 72499, "2nd_quote_post": 1, "2nd_quote_stack": 121, "2nd_quote_buyout": 72500, "3rd_quote_post": 4, "3rd_quote_stack": 10, "3rd_quote_buyout": 74000}, {"date&time": "2019-03-12 19:45 (Tuesday", "1st_quote_post": 7, "1st_quote_stack": 100, "1st_quote_buyout": 72499, "2nd_quote_post": 1, "2nd_quote_stack": 121, "2nd_quote_buyout": 72500, "3rd_quote_post": 4, "3rd_quote_stack": 10, "3rd_quote_buyout": 74000}, {"date&time": "2019-03-12 20:07 (Tuesday", "1st_quote_post": 2, "1st_quote_stack": 200, "1st_quote_buyout": 72000, "2nd_quote_post": 7, "2nd_quote_stack": 100, "2nd_quote_buyout": 72499, "3rd_quote_post": 1, "3rd_quote_stack": 121, "3rd_quote_buyout": 72500}, {"date&time": "2019-03-12 20:27 (Tuesday", "1st_quote_post": 6, "1st_quote_stack": 100, "1st_quote_buyout": 71999, "2nd_quote_post": 7, "2nd_quote_stack": 100, "2nd_quote_buyout": 72499, "3rd_quote_post": 1, "3rd_quote_stack": 121, "3rd_quote_buyout": 72500}, {"date&time": "2019-03-12 20:48 (Tuesday", "1st_quote_post": 3, "1st_quote_stack": 100, "1st_quote_buyout": 71999, "2nd_quote_post": 7, "2nd_quote_stack": 100, "2nd_quote_buyout": 72499, "3rd_quote_post": 1, "3rd_quote_stack": 121, "3rd_quote_buyout": 72500}, {"date&time": "2019-03-12 21:08 (Tuesday", "1st_quote_post": 3, "1st_quote_stack": 100, "1st_quote_buyout": 71999, "2nd_quote_post": 7, "2nd_quote_stack": 100, "2nd_quote_buyout": 72499, "3rd_quote_post": 1, "3rd_quote_stack": 121, "3rd_quote_buyout": 72500}, {"date&time": "2019-03-12 21:28 (Tuesday", "1st_quote_post": 3, "1st_quote_stack": 100, "1st_quote_buyout": 71999, "2nd_quote_post": 7, "2nd_quote_stack": 100, "2nd_quote_buyout": 72499, "3rd_quote_post": 1, "3rd_quote_stack": 121, "3rd_quote_buyout": 72500}, {"date&time": "2019-03-12 21:49 (Tuesday", "1st_quote_post": 2, "1st_quote_stack": 200, "1st_quote_buyout": 70199, "2nd_quote_post": 1, "2nd_quote_stack": 138, "2nd_quote_buyout": 70199, "3rd_quote_post": 3, "3rd_quote_stack": 100, "3rd_quote_buyout": 71999}, {"date&time": "2019-03-12 22:06 (Tuesday", "1st_quote_post": 6, "1st_quote_stack": 100, "1st_quote_buyout": 70198, "2nd_quote_post": 2, "2nd_quote_stack": 200, "2nd_quote_buyout": 70199, "3rd_quote_post": 1, "3rd_quote_stack": 138, "3rd_quote_buyout": 70199}, {"date&time": "2019-03-12 22:27 (Tuesday", "1st_quote_post": 1, "1st_quote_stack": 23, "1st_quote_buyout": 61017, "2nd_quote_post": 5, "2nd_quote_stack": 100, "2nd_quote_buyout": 70198, "3rd_quote_post": 2, "3rd_quote_stack": 200, "3rd_quote_buyout": 70199}, {"date&time": "2019-03-12 22:45 (Tuesday", "1st_quote_post": 1, "1st_quote_stack": 23, "1st_quote_buyout": 61017, "2nd_quote_post": 4, "2nd_quote_stack": 100, "2nd_quote_buyout": 70198, "3rd_quote_post": 2, "3rd_quote_stack": 200, "3rd_quote_buyout": 70199}, {"date&time": "2019-03-12 23:03 (Tuesday", "1st_quote_post": 1, "1st_quote_stack": 23, "1st_quote_buyout": 61017, "2nd_quote_post": 4, "2nd_quote_stack": 100, "2nd_quote_buyout": 70198, "3rd_quote_post": 2, "3rd_quote_stack": 200, "3rd_quote_buyout": 70199}, {"date&time": "2019-03-12 23:22 (Tuesday", "1st_quote_post": 1, "1st_quote_stack": 25, "1st_quote_buyout": 50000, "2nd_quote_post": 1, "2nd_quote_stack": 23, "2nd_quote_buyout": 61017, "3rd_quote_post": 4, "3rd_quote_stack": 100, "3rd_quote_buyout": 70198}, {"date&time": "2019-03-12 23:39 (Tuesday", "1st_quote_post": 1, "1st_quote_stack": 25, "1st_quote_buyout": 50000, "2nd_quote_post": 1, "2nd_quote_stack": 23, "2nd_quote_buyout": 61017, "3rd_quote_post": 4, "3rd_quote_stack": 100, "3rd_quote_buyout": 70198}, {"date&time": "2019-03-12 23:58 (Tuesday", "1st_quote_post": 1, "1st_quote_stack": 25, "1st_quote_buyout": 50000, "2nd_quote_post": 1, "2nd_quote_stack": 23, "2nd_quote_buyout": 61017, "3rd_quote_post": 1, "3rd_quote_stack": 138, "3rd_quote_buyout": 70199}, {"date&time": "2019-03-13 00:19 (Wednesday", "1st_quote_post": 1, "1st_quote_stack": 25, "1st_quote_buyout": 50000, "2nd_quote_post": 1, "2nd_quote_stack": 23, "2nd_quote_buyout": 61017, "3rd_quote_post": 2, "3rd_quote_stack": 100, "3rd_quote_buyout": 70198}, {"date&time": "2019-03-13 00:44 (Wednesday", "1st_quote_post": 1, "1st_quote_stack": 25, "1st_quote_buyout": 50000, "2nd_quote_post": 1, "2nd_quote_stack": 23, "2nd_quote_buyout": 61017, "3rd_quote_post": 1, "3rd_quote_stack": 32, "3rd_quote_buyout": 64000}, {"date&time": "2019-03-13 01:10 (Wednesday", "1st_quote_post": 1, "1st_quote_stack": 25, "1st_quote_buyout": 50000, "2nd_quote_post": 1, "2nd_quote_stack": 23, "2nd_quote_buyout": 61017, "3rd_quote_post": 1, "3rd_quote_stack": 32, "3rd_quote_buyout": 64000}, {"date&time": "2019-03-13 01:34 (Wednesday", "1st_quote_post": 1, "1st_quote_stack": 25, "1st_quote_buyout": 50000, "2nd_quote_post": 1, "2nd_quote_stack": 32, "2nd_quote_buyout": 64000, "3rd_quote_post": 1, "3rd_quote_stack": 121, "3rd_quote_buyout": 72500}, {"date&time": "2019-03-13 02:01 (Wednesday", "1st_quote_post": 4, "1st_quote_stack": 100, "1st_quote_buyout": 72499, "2nd_quote_post": 1, "2nd_quote_stack": 121, "2nd_quote_buyout": 72500, "3rd_quote_post": 2, "3rd_quote_stack": 10, "3rd_quote_buyout": 74000}, {"date&time": "2019-03-13 02:26 (Wednesday", "1st_quote_post": 4, "1st_quote_stack": 100, "1st_quote_buyout": 72499, "2nd_quote_post": 1, "2nd_quote_stack": 121, "2nd_quote_buyout": 72500, "3rd_quote_post": 2, "3rd_quote_stack": 10, "3rd_quote_buyout": 74000}, {"date&time": "2019-03-13 02:52 (Wednesday", "1st_quote_post": 4, "1st_quote_stack": 100, "1st_quote_buyout": 72499, "2nd_quote_post": 1, "2nd_quote_stack": 121, "2nd_quote_buyout": 72500, "3rd_quote_post": 2, "3rd_quote_stack": 10, "3rd_quote_buyout": 74000}, {"date&time": "2019-03-13 03:16 (Wednesday", "1st_quote_post": 4, "1st_quote_stack": 100, "1st_quote_buyout": 72499, "2nd_quote_post": 1, "2nd_quote_stack": 121, "2nd_quote_buyout": 72500, "3rd_quote_post": 2, "3rd_quote_stack": 10, "3rd_quote_buyout": 74000}, {"date&time": "2019-03-13 03:42 (Wednesday", "1st_quote_post": 2, "1st_quote_stack": 100, "1st_quote_buyout": 72499, "2nd_quote_post": 1, "2nd_quote_stack": 121, "2nd_quote_buyout": 72500, "3rd_quote_post": 2, "3rd_quote_stack": 10, "3rd_quote_buyout": 74000}, {"date&time": "2019-03-13 04:05 (Wednesday", "1st_quote_post": 2, "1st_quote_stack": 100, "1st_quote_buyout": 72499, "2nd_quote_post": 1, "2nd_quote_stack": 121, "2nd_quote_buyout": 72500, "3rd_quote_post": 2, "3rd_quote_stack": 10, "3rd_quote_buyout": 74000}, {"date&time": "2019-03-13 08:05 (Wednesday", "1st_quote_post": 2, "1st_quote_stack": 100, "1st_quote_buyout": 72499, "2nd_quote_post": 2, "2nd_quote_stack": 10, "2nd_quote_buyout": 74000, "3rd_quote_post": 1, "3rd_quote_stack": 5, "3rd_quote_buyout": 79000}, {"date&time": "2019-03-13 08:09 (Wednesday", "1st_quote_post": 2, "1st_quote_stack": 100, "1st_quote_buyout": 72499, "2nd_quote_post": 2, "2nd_quote_stack": 10, "2nd_quote_buyout": 74000, "3rd_quote_post": 1, "3rd_quote_stack": 5, "3rd_quote_buyout": 79000}, {"date&time": "2019-03-13 08:32 (Wednesday", "1st_quote_post": 2, "1st_quote_stack": 100, "1st_quote_buyout": 72499, "2nd_quote_post": 2, "2nd_quote_stack": 10, "2nd_quote_buyout": 74000, "3rd_quote_post": 1, "3rd_quote_stack": 5, "3rd_quote_buyout": 79000}, {"date&time": "2019-03-13 08:56 (Wednesday", "1st_quote_post": 2, "1st_quote_stack": 100, "1st_quote_buyout": 72499, "2nd_quote_post": 2, "2nd_quote_stack": 10, "2nd_quote_buyout": 74000, "3rd_quote_post": 1, "3rd_quote_stack": 5, "3rd_quote_buyout": 79000}]